dbt_correlator/__init__.py
dbt_correlator/cli.py
dbt_correlator/config.py
dbt_correlator/emitter.py
dbt_correlator/parser.py
correlator_dbt-0.1.0.dist-info/METADATA
correlator_dbt-0.1.0.dist-info/WHEEL
correlator_dbt-0.1.0.dist-info/entry_points.txt
correlator_dbt-0.1.0.dist-info/licenses/LICENSE
correlator_dbt-0.1.0.dist-info/RECORD
