Metadata-Version: 2.4
Name: correlator-dbt
Version: 0.1.0
Summary: dbt plugin that emits OpenLineage events with test results for automated incident correlation
Project-URL: Homepage, https://github.com/correlator-io/correlator-dbt
Project-URL: Repository, https://github.com/correlator-io/correlator-dbt
Project-URL: Documentation, https://github.com/correlator-io/correlator-dbt#readme
Project-URL: Bug Tracker, https://github.com/correlator-io/correlator-dbt/issues
Project-URL: Correlator, https://github.com/correlator-io/correlator
Author-email: Emmanuel King Kasulani <kasulani@gmail.com>
License: Apache-2.0
License-File: LICENSE
Keywords: correlation,data-quality,dbt,incident-management,lineage,observability,openlineage,testing
Classifier: Development Status :: 3 - Alpha
Classifier: Intended Audience :: Developers
Classifier: Intended Audience :: Information Technology
Classifier: License :: OSI Approved :: Apache Software License
Classifier: Programming Language :: Python :: 3
Classifier: Programming Language :: Python :: 3.9
Classifier: Programming Language :: Python :: 3.10
Classifier: Programming Language :: Python :: 3.11
Classifier: Programming Language :: Python :: 3.12
Classifier: Programming Language :: Python :: 3.13
Classifier: Topic :: Software Development :: Quality Assurance
Classifier: Topic :: Software Development :: Testing
Classifier: Topic :: System :: Monitoring
Requires-Python: >=3.9
Requires-Dist: click>=8.1.0
Requires-Dist: openlineage-python>=1.0.0
Requires-Dist: pyyaml>=6.0
Requires-Dist: requests>=2.28.0
Provides-Extra: dev
Requires-Dist: bandit[toml]>=1.7.0; extra == 'dev'
Requires-Dist: black>=23.0.0; extra == 'dev'
Requires-Dist: isort>=5.13.0; extra == 'dev'
Requires-Dist: mypy>=1.9.0; extra == 'dev'
Requires-Dist: pre-commit>=3.5.0; extra == 'dev'
Requires-Dist: pytest-cov>=4.1.0; extra == 'dev'
Requires-Dist: pytest-mock>=3.11.0; extra == 'dev'
Requires-Dist: pytest>=7.4.0; extra == 'dev'
Requires-Dist: ruff>=0.8.0; extra == 'dev'
Requires-Dist: types-click>=7.1.0; extra == 'dev'
Provides-Extra: docs
Requires-Dist: myst-parser>=2.0.0; extra == 'docs'
Requires-Dist: sphinx-rtd-theme>=1.0.0; extra == 'docs'
Requires-Dist: sphinx>=7.0.0; extra == 'docs'
